{"_type":"export","__export_format":4,"__export_date":"2024-12-05T22:10:01.925Z","__export_source":"insomnia.desktop.app:v9.3.3","resources":[{"_id":"req_cb2b8c1398d0467191633333be8364e5","parentId":"fld_6f46aee7997c49519eff67836b7ad60f","modified":1733435268169,"created":1733425935409,"url":"{{ _.apiUrl }}/api/v1/users","name":"GetAll","description":"","method":"GET","body":{},"parameters":[{"id":"pair_79866a94573248aea4f5a9642844bacf","name":"page","value":"0","description":"","disabled":false},{"id":"pair_4e0469217cea4f6bb2fd759bddb2c89b","name":"size","value":"10","description":"","disabled":false}],"headers":[{"name":"User-Agent","value":"insomnia/9.3.3"}],"authentication":{},"metaSortKey":-1733425895068,"isPrivate":false,"pathParameters":[],"settingStoreCookies":true,"settingSendCookies":true,"settingDisableRenderRequestBody":false,"settingEncodeUrl":true,"settingRebuildPath":true,"settingFollowRedirects":"global","_type":"request"},{"_id":"fld_6f46aee7997c49519eff67836b7ad60f","parentId":"fld_9cc7088e7e7947f8a21243994474b607","modified":1733425889615,"created":1733425889615,"name":"users","description":"","environment":{},"environmentPropertyOrder":null,"metaSortKey":-1733425889615,"_type":"request_group"},{"_id":"fld_9cc7088e7e7947f8a21243994474b607","parentId":"fld_b936e16c6c4447cda8bbb061c536c8f0","modified":1733425848179,"created":1733425848179,"name":"v1","description":"","environment":{},"environmentPropertyOrder":null,"metaSortKey":-1733425848179,"_type":"request_group"},{"_id":"fld_b936e16c6c4447cda8bbb061c536c8f0","parentId":"wrk_a1e3df84e4fe44c7b7de51b7fbf1d8c9","modified":1733425840966,"created":1733425840966,"name":"api","description":"","environment":{},"environmentPropertyOrder":null,"metaSortKey":-1733425840966,"_type":"request_group"},{"_id":"wrk_a1e3df84e4fe44c7b7de51b7fbf1d8c9","parentId":null,"modified":1733425832557,"created":1733425832557,"name":"event_ticket_exchange","description":"","scope":"collection","_type":"workspace"},{"_id":"req_9a7066ef53094ff6aeb7360014b2c0e2","parentId":"fld_6f46aee7997c49519eff67836b7ad60f","modified":1733425926313,"created":1733425894968,"url":"{{ _.apiUrl }}/api/v1/users/1","name":"GetById","description":"","method":"GET","body":{},"parameters":[],"headers":[{"name":"User-Agent","value":"insomnia/9.3.3"}],"authentication":{},"metaSortKey":-1733425894968,"isPrivate":false,"pathParameters":[],"settingStoreCookies":true,"settingSendCookies":true,"settingDisableRenderRequestBody":false,"settingEncodeUrl":true,"settingRebuildPath":true,"settingFollowRedirects":"global","_type":"request"},{"_id":"req_a1e8784feb6a4389a5063173eccc2acc","parentId":"fld_b454109954e24b7cb779e0984abd928c","modified":1733436039412,"created":1733427114776,"url":"{{ _.apiUrl }}/api/v1/venues","name":"GetAll","description":"","method":"GET","body":{},"parameters":[{"id":"pair_7b888a782f9546d8b28afdd478aec8d9","name":"page","value":"0","description":"","disabled":false},{"id":"pair_971211c6881948f7b75bf74023ac5e6e","name":"size","value":"10","description":"","disabled":false}],"headers":[{"name":"User-Agent","value":"insomnia/9.3.3"}],"authentication":{},"metaSortKey":-1733425895068,"isPrivate":false,"pathParameters":[],"settingStoreCookies":true,"settingSendCookies":true,"settingDisableRenderRequestBody":false,"settingEncodeUrl":true,"settingRebuildPath":true,"settingFollowRedirects":"global","_type":"request"},{"_id":"fld_b454109954e24b7cb779e0984abd928c","parentId":"fld_9cc7088e7e7947f8a21243994474b607","modified":1733427114775,"created":1733427114775,"name":"venues","description":"","environment":{},"environmentPropertyOrder":null,"metaSortKey":-1733425868897,"_type":"request_group"},{"_id":"req_a5ccc620adf04558ac921816a86f8ba4","parentId":"fld_b454109954e24b7cb779e0984abd928c","modified":1733427195625,"created":1733427114776,"url":"{{ _.apiUrl }}/api/v1/venues/1","name":"GetById","description":"","method":"GET","body":{},"parameters":[],"headers":[{"name":"User-Agent","value":"insomnia/9.3.3"}],"authentication":{},"metaSortKey":-1733425894968,"isPrivate":false,"pathParameters":[],"settingStoreCookies":true,"settingSendCookies":true,"settingDisableRenderRequestBody":false,"settingEncodeUrl":true,"settingRebuildPath":true,"settingFollowRedirects":"global","_type":"request"},{"_id":"req_5245c1f415034d6295849af5af68c700","parentId":"fld_7d99c250f8b74ff89fef8cb2c3a38c1a","modified":1733436048784,"created":1733427124057,"url":"{{ _.apiUrl }}/api/v1/categories","name":"GetAll","description":"","method":"GET","body":{},"parameters":[{"id":"pair_621d9a54396549b4a5421d577e45246d","name":"page","value":"0","description":"","disabled":false},{"id":"pair_f9fb0d8cb3f940ab940a8d6ae2724c26","name":"size","value":"10","description":"","disabled":false}],"headers":[{"name":"User-Agent","value":"insomnia/9.3.3"}],"authentication":{},"metaSortKey":-1733425895068,"isPrivate":false,"pathParameters":[],"settingStoreCookies":true,"settingSendCookies":true,"settingDisableRenderRequestBody":false,"settingEncodeUrl":true,"settingRebuildPath":true,"settingFollowRedirects":"global","_type":"request"},{"_id":"fld_7d99c250f8b74ff89fef8cb2c3a38c1a","parentId":"fld_9cc7088e7e7947f8a21243994474b607","modified":1733427124056,"created":1733427124056,"name":"categories","description":"","environment":{},"environmentPropertyOrder":null,"metaSortKey":-1733425858538,"_type":"request_group"},{"_id":"req_eee5cd57496a4a45a22ae1bd655028eb","parentId":"fld_7d99c250f8b74ff89fef8cb2c3a38c1a","modified":1733427209073,"created":1733427124066,"url":"{{ _.apiUrl }}/api/v1/categories/1","name":"GetById","description":"","method":"GET","body":{},"parameters":[],"headers":[{"name":"User-Agent","value":"insomnia/9.3.3"}],"authentication":{},"metaSortKey":-1733425894968,"isPrivate":false,"pathParameters":[],"settingStoreCookies":true,"settingSendCookies":true,"settingDisableRenderRequestBody":false,"settingEncodeUrl":true,"settingRebuildPath":true,"settingFollowRedirects":"global","_type":"request"},{"_id":"req_b5d42eec9c044efc92c93fc6d0b865d8","parentId":"fld_9b3ff65d41da4cd6840d887f41cb9c08","modified":1733436058260,"created":1733427133829,"url":"{{ _.apiUrl }}/api/v1/dates","name":"GetAll","description":"","method":"GET","body":{},"parameters":[{"id":"pair_81411be59e954afda40e0a47b0eef19d","name":"page","value":"0","description":"","disabled":false},{"id":"pair_cf284cfaf99a479b885314cb1c7c90de","name":"size","value":"10","description":"","disabled":false}],"headers":[{"name":"User-Agent","value":"insomnia/9.3.3"}],"authentication":{},"metaSortKey":-1733425895068,"isPrivate":false,"pathParameters":[],"settingStoreCookies":true,"settingSendCookies":true,"settingDisableRenderRequestBody":false,"settingEncodeUrl":true,"settingRebuildPath":true,"settingFollowRedirects":"global","_type":"request"},{"_id":"fld_9b3ff65d41da4cd6840d887f41cb9c08","parentId":"fld_9cc7088e7e7947f8a21243994474b607","modified":1733427133829,"created":1733427133829,"name":"dates","description":"","environment":{},"environmentPropertyOrder":null,"metaSortKey":-1733425853358.5,"_type":"request_group"},{"_id":"req_5dc5fd25edfe4e9f9b712cbef1adf2ad","parentId":"fld_9b3ff65d41da4cd6840d887f41cb9c08","modified":1733436142716,"created":1733427133830,"url":"{{ _.apiUrl }}/api/v1/dates/1827","name":"GetById","description":"","method":"GET","body":{},"parameters":[],"headers":[{"name":"User-Agent","value":"insomnia/9.3.3"}],"authentication":{},"metaSortKey":-1733425894968,"isPrivate":false,"pathParameters":[],"settingStoreCookies":true,"settingSendCookies":true,"settingDisableRenderRequestBody":false,"settingEncodeUrl":true,"settingRebuildPath":true,"settingFollowRedirects":"global","_type":"request"},{"_id":"req_9eaf6a63c07844ac9e4088cf59144d62","parentId":"fld_1d555176fc6a44a3948bb0608e8b8e7f","modified":1733436072558,"created":1733427145008,"url":"{{ _.apiUrl }}/api/v1/events","name":"GetAll","description":"","method":"GET","body":{},"parameters":[{"id":"pair_b4be8f041f7f4daaa9d6cab9b4bcff97","name":"page","value":"0","description":"","disabled":false},{"id":"pair_bcce8140570f45459659d94331b1d35d","name":"size","value":"10","description":"","disabled":false}],"headers":[{"name":"User-Agent","value":"insomnia/9.3.3"}],"authentication":{},"metaSortKey":-1733425895068,"isPrivate":false,"pathParameters":[],"settingStoreCookies":true,"settingSendCookies":true,"settingDisableRenderRequestBody":false,"settingEncodeUrl":true,"settingRebuildPath":true,"settingFollowRedirects":"global","_type":"request"},{"_id":"fld_1d555176fc6a44a3948bb0608e8b8e7f","parentId":"fld_9cc7088e7e7947f8a21243994474b607","modified":1733427145007,"created":1733427145007,"name":"events","description":"","environment":{},"environmentPropertyOrder":null,"metaSortKey":-1733425850768.75,"_type":"request_group"},{"_id":"req_79f5ce9da1bf4b2480d7e1ec7ef3c1ed","parentId":"fld_1d555176fc6a44a3948bb0608e8b8e7f","modified":1733427232514,"created":1733427145008,"url":"{{ _.apiUrl }}/api/v1/events/1","name":"GetById","description":"","method":"GET","body":{},"parameters":[],"headers":[{"name":"User-Agent","value":"insomnia/9.3.3"}],"authentication":{},"metaSortKey":-1733425894968,"isPrivate":false,"pathParameters":[],"settingStoreCookies":true,"settingSendCookies":true,"settingDisableRenderRequestBody":false,"settingEncodeUrl":true,"settingRebuildPath":true,"settingFollowRedirects":"global","_type":"request"},{"_id":"req_1b18bff1ced244c5b2a6e5b9fb6ed1d7","parentId":"fld_be55ab8bf0e8449bb98d2fc03d3ed3ee","modified":1733436083665,"created":1733427159215,"url":"{{ _.apiUrl }}/api/v1/listings","name":"GetAll","description":"","method":"GET","body":{},"parameters":[{"id":"pair_61fef7505f534592960bc94583921176","name":"page","value":"0","description":"","disabled":false},{"id":"pair_e15721aed5984affa908752886c3dbb9","name":"size","value":"10","description":"","disabled":false}],"headers":[{"name":"User-Agent","value":"insomnia/9.3.3"}],"authentication":{},"metaSortKey":-1733425895068,"isPrivate":false,"pathParameters":[],"settingStoreCookies":true,"settingSendCookies":true,"settingDisableRenderRequestBody":false,"settingEncodeUrl":true,"settingRebuildPath":true,"settingFollowRedirects":"global","_type":"request"},{"_id":"fld_be55ab8bf0e8449bb98d2fc03d3ed3ee","parentId":"fld_9cc7088e7e7947f8a21243994474b607","modified":1733427166534,"created":1733427159213,"name":"listings","description":"","environment":{},"environmentPropertyOrder":null,"metaSortKey":-1733425849473.875,"_type":"request_group"},{"_id":"req_2a6739e69aaf4120b76f972dd9739058","parentId":"fld_be55ab8bf0e8449bb98d2fc03d3ed3ee","modified":1733427245901,"created":1733427159214,"url":"{{ _.apiUrl }}/api/v1/listings/1","name":"GetById","description":"","method":"GET","body":{},"parameters":[],"headers":[{"name":"User-Agent","value":"insomnia/9.3.3"}],"authentication":{},"metaSortKey":-1733425894968,"isPrivate":false,"pathParameters":[],"settingStoreCookies":true,"settingSendCookies":true,"settingDisableRenderRequestBody":false,"settingEncodeUrl":true,"settingRebuildPath":true,"settingFollowRedirects":"global","_type":"request"},{"_id":"req_5bd1cdc6b9d647a6a352798f9232cbbc","parentId":"fld_6037282daed34b8d860e1933143164fa","modified":1733436092395,"created":1733427174754,"url":"{{ _.apiUrl }}/api/v1/sales","name":"GetAll","description":"","method":"GET","body":{},"parameters":[{"id":"pair_c5479e93f2144fb69f13e5c70a143422","name":"page","value":"0","description":"","disabled":false},{"id":"pair_31e7a9f4e07541839792262e07e0ef1a","name":"size","value":"10","description":"","disabled":false}],"headers":[{"name":"User-Agent","value":"insomnia/9.3.3"}],"authentication":{},"metaSortKey":-1733425895068,"isPrivate":false,"pathParameters":[],"settingStoreCookies":true,"settingSendCookies":true,"settingDisableRenderRequestBody":false,"settingEncodeUrl":true,"settingRebuildPath":true,"settingFollowRedirects":"global","_type":"request"},{"_id":"fld_6037282daed34b8d860e1933143164fa","parentId":"fld_9cc7088e7e7947f8a21243994474b607","modified":1733427174752,"created":1733427174752,"name":"sales","description":"","environment":{},"environmentPropertyOrder":null,"metaSortKey":-1733425848826.4375,"_type":"request_group"},{"_id":"req_ce20c59f20564dbba1ea7351a78603a0","parentId":"fld_6037282daed34b8d860e1933143164fa","modified":1733427259154,"created":1733427174753,"url":"{{ _.apiUrl }}/api/v1/sales/1","name":"GetById","description":"","method":"GET","body":{},"parameters":[],"headers":[{"name":"User-Agent","value":"insomnia/9.3.3"}],"authentication":{},"metaSortKey":-1733425894968,"isPrivate":false,"pathParameters":[],"settingStoreCookies":true,"settingSendCookies":true,"settingDisableRenderRequestBody":false,"settingEncodeUrl":true,"settingRebuildPath":true,"settingFollowRedirects":"global","_type":"request"},{"_id":"env_d4cd4cb81f7988760bb078ca432bb1b8066be1b6","parentId":"wrk_a1e3df84e4fe44c7b7de51b7fbf1d8c9","modified":1733425875973,"created":1733425832570,"name":"Base Environment","data":{"apiUrl":"http://localhost:8080"},"dataPropertyOrder":{"&":["apiUrl"]},"color":null,"isPrivate":false,"metaSortKey":1733425832570,"_type":"environment"},{"_id":"jar_d4cd4cb81f7988760bb078ca432bb1b8066be1b6","parentId":"wrk_a1e3df84e4fe44c7b7de51b7fbf1d8c9","modified":1733425832588,"created":1733425832588,"name":"Default Jar","cookies":[],"_type":"cookie_jar"}]}